makeraily/utils/base.py
makeraily/utils/card.py
makeraily/utils/template.py
makeraily/utils/time.py
makeraily-0.1.1.dist-info/LICENSE
makeraily-0.1.1.dist-info/METADATA
makeraily-0.1.1.dist-info/WHEEL
makeraily-0.1.1.dist-info/RECORD
