Metadata-Version: 2.1
Name: makeraily
Version: 0.1.1
Summary: aily python in code node
Author: jg
Author-email: jg@bytedance.com
Requires-Python: >=3.12,<4.0
Classifier: Programming Language :: Python :: 3
Classifier: Programming Language :: Python :: 3.12
Requires-Dist: jinja2 (>=3.1.4,<4.0.0)
Requires-Dist: langchain (>=0.2.14,<0.3.0)
Requires-Dist: pytz (>=2024.1,<2025.0)
